MANIFEST.in
README.md
setup.cfg
setup.py
pymms/__init__.py
pymms/drawing.py
pymms/mms.py
pymms/mms_ex.py
pymms/prettytable.py
pymms/print_results.py
pymms/research_instruments.py
pymms.egg-info/PKG-INFO
pymms.egg-info/SOURCES.txt
pymms.egg-info/dependency_links.txt
pymms.egg-info/not-zip-safe
pymms.egg-info/requires.txt
pymms.egg-info/top_level.txt