Metadata-Version: 1.0
Name: pymms
Version: 1.0.8
Summary: Simulation of the Minkowski metric  for Python
Home-page: https://vgurianov.github.io/srt/mms/
Author: Vasyliy I. Gurianov
Author-email: vg2007sns@rambler.ru
License: MIT
Platform: UNKNOWN
